{
  "type": "minecraft:generic",
  "pools": [
    {
      "rolls": 2,
      "entries": [
        {
          "type": "minecraft:empty",
          "weight": 50
        },
        {
          "type": "minecraft:item",
          "name": "minecraft:ink_sac",
          "weight": 10
        },
        {
          "type": "minecraft:item",
          "name": "minecraft:emerald",
          "weight": 20
        }
      ]
    },
    {
      "rolls": 1,
      "entries": [
        {
          "type": "minecraft:empty",
          "weight": 995
        },
        {
          "type": "minecraft:item",
          "name": "minecraft:glistering_melon_slice",
          "weight": 5
        },
        {
          "type": "minecraft:item",
          "name": "minecraft:ghast_tear",
          "weight": 3
        }
      ]
    }
  ]
}